fmus_vox/__init__.py
fmus_vox/api/__init__.py
fmus_vox/api/app.py
fmus_vox/api/models.py
fmus_vox/chatbot/__init__.py
fmus_vox/chatbot/agents.py
fmus_vox/chatbot/conversation.py
fmus_vox/chatbot/llm.py
fmus_vox/cli/__init__.py
fmus_vox/cli/commands.py
fmus_vox/cli/helpers.py
fmus_vox/core/__init__.py
fmus_vox/core/audio.py
fmus_vox/core/config.py
fmus_vox/core/errors.py
fmus_vox/core/logging.py
fmus_vox/core/phonemizer.py
fmus_vox/core/utils.py
fmus_vox/gui/__init__.py
fmus_vox/gui/app.py
fmus_vox/stream/__init__.py
fmus_vox/stream/audioplayer.py
fmus_vox/stream/microphone.py
fmus_vox/stream/voice_stream.py
fmus_vox/stream/websocket.py
fmus_vox/stt/__init__.py
fmus_vox/stt/speechbrain.py
fmus_vox/stt/transcriber.py
fmus_vox/stt/wav2vec.py
fmus_vox/stt/whisper.py
fmus_vox/tts/__init__.py
fmus_vox/tts/coqui.py
fmus_vox/tts/elevenlabs.py
fmus_vox/tts/fastspeech.py
fmus_vox/tts/speaker.py
fmus_vox/tts/vits.py
fmus_vox/voice/__init__.py
fmus_vox/voice/clone.py
fmus_vox/voice/cloner.py
fmus_vox/voice/enhance.py
fmus_vox/voice/sv2tts.py
fmus_vox/voice/transform.py
fmus_vox/voice/yourtts.py
fmus_vox/voice/sv2tts_utils/__init__.py
fmus_vox/voice/sv2tts_utils/encoder.py
fmus_vox/voice/sv2tts_utils/synthesizer.py
fmus_vox/voice/sv2tts_utils/vocoder.py
fmus_vox/wakeword/__init__.py
fmus_vox/wakeword/detector.py
fmus_vox/wakeword/porcupine.py
fmus_vox/wakeword/precise.py
fmus_vox-0.0.1.dist-info/licenses/LICENSE
tests/__init__.py
tests/test_audio.py
fmus_vox-0.0.1.dist-info/METADATA
fmus_vox-0.0.1.dist-info/WHEEL
fmus_vox-0.0.1.dist-info/entry_points.txt
fmus_vox-0.0.1.dist-info/top_level.txt
fmus_vox-0.0.1.dist-info/RECORD
