Metadata-Version: 2.4
Name: fmus-vox
Version: 0.0.1
Summary: A speech processing library
Home-page: https://github.com/mexyusef/fmus-vox
Author: Yusef Ulum
Author-email: yusef314159@gmail.com
Project-URL: Bug Tracker, https://github.com/mexyusef/fmus-vox/issues
Project-URL: Documentation, https://fmus-vox.readthedocs.io/
Project-URL: Source Code, https://github.com/mexyusef/fmus-vox
Classifier: Development Status :: 3 - Alpha
Classifier: Intended Audience :: Developers
Classifier: License :: OSI Approved :: MIT License
Classifier: Programming Language :: Python :: 3
Classifier: Programming Language :: Python :: 3.8
Classifier: Programming Language :: Python :: 3.9
Classifier: Programming Language :: Python :: 3.10
Classifier: Programming Language :: Python :: 3.11
Classifier: Topic :: Multimedia :: Sound/Audio :: Speech
Classifier: Topic :: Scientific/Engineering :: Artificial Intelligence
Requires-Python: >=3.8
License-File: LICENSE
Requires-Dist: numpy>=1.20.0
Requires-Dist: scipy>=1.7.0
Requires-Dist: librosa>=0.9.0
Requires-Dist: soundfile>=0.10.0
Requires-Dist: pyrubberband>=0.3.0
Requires-Dist: sounddevice>=0.4.0
Requires-Dist: requests>=2.27.0
Requires-Dist: tqdm>=4.62.0
Requires-Dist: pydantic>=1.9.0
Provides-Extra: stt
Requires-Dist: torch>=1.10.0; extra == "stt"
Requires-Dist: openai-whisper>=20230314; extra == "stt"
Requires-Dist: transformers>=4.18.0; extra == "stt"
Requires-Dist: pyctcdecode>=0.3.0; extra == "stt"
Provides-Extra: tts
Requires-Dist: torch>=1.10.0; extra == "tts"
Requires-Dist: torchaudio>=0.10.0; extra == "tts"
Requires-Dist: phonemizer>=3.0.0; extra == "tts"
Requires-Dist: unidecode>=1.3.0; extra == "tts"
Provides-Extra: voice
Requires-Dist: torch>=1.10.0; extra == "voice"
Requires-Dist: resemblyzer>=0.1.0; extra == "voice"
Requires-Dist: praat-parselmouth>=0.4.0; extra == "voice"
Requires-Dist: phonemizer>=3.0.0; extra == "voice"
Requires-Dist: gruut>=2.0.0; platform_system != "Windows" and extra == "voice"
Requires-Dist: unidecode>=1.3.0; extra == "voice"
Provides-Extra: voice-yourtts
Requires-Dist: TTS>=0.10.0; extra == "voice-yourtts"
Provides-Extra: voice-sv2tts
Requires-Dist: tensorflow==1.15.0; python_version < "3.10" and extra == "voice-sv2tts"
Requires-Dist: numpy==1.19.3; python_version < "3.10" and extra == "voice-sv2tts"
Requires-Dist: librosa==0.8.0; python_version < "3.10" and extra == "voice-sv2tts"
Requires-Dist: webrtcvad==2.0.10; extra == "voice-sv2tts"
Requires-Dist: inflect>=5.3.0; extra == "voice-sv2tts"
Provides-Extra: wakeword
Requires-Dist: pvporcupine>=2.1.0; extra == "wakeword"
Requires-Dist: webrtcvad>=2.0.10; extra == "wakeword"
Provides-Extra: api
Requires-Dist: fastapi>=0.75.0; extra == "api"
Requires-Dist: uvicorn>=0.17.0; extra == "api"
Requires-Dist: python-multipart>=0.0.5; extra == "api"
Provides-Extra: cli
Requires-Dist: typer>=0.4.0; extra == "cli"
Requires-Dist: rich>=12.0.0; extra == "cli"
Provides-Extra: chatbot
Requires-Dist: langchain>=0.0.139; extra == "chatbot"
Provides-Extra: dev
Requires-Dist: pytest>=7.0.0; extra == "dev"
Requires-Dist: pytest-cov>=3.0.0; extra == "dev"
Requires-Dist: black>=22.1.0; extra == "dev"
Requires-Dist: isort>=5.10.0; extra == "dev"
Requires-Dist: mypy>=0.931; extra == "dev"
Requires-Dist: flake8>=4.0.0; extra == "dev"
Requires-Dist: sphinx>=4.4.0; extra == "dev"
Requires-Dist: sphinx-rtd-theme>=1.0.0; extra == "dev"
Provides-Extra: voice-all
Requires-Dist: TTS>=0.10.0; extra == "voice-all"
Requires-Dist: gruut>=2.0.0; platform_system != "Windows" and extra == "voice-all"
Requires-Dist: inflect>=5.3.0; extra == "voice-all"
Requires-Dist: librosa==0.8.0; python_version < "3.10" and extra == "voice-all"
Requires-Dist: numpy==1.19.3; python_version < "3.10" and extra == "voice-all"
Requires-Dist: phonemizer>=3.0.0; extra == "voice-all"
Requires-Dist: praat-parselmouth>=0.4.0; extra == "voice-all"
Requires-Dist: resemblyzer>=0.1.0; extra == "voice-all"
Requires-Dist: tensorflow==1.15.0; python_version < "3.10" and extra == "voice-all"
Requires-Dist: torch>=1.10.0; extra == "voice-all"
Requires-Dist: unidecode>=1.3.0; extra == "voice-all"
Requires-Dist: webrtcvad==2.0.10; extra == "voice-all"
Provides-Extra: full
Requires-Dist: TTS>=0.10.0; extra == "full"
Requires-Dist: black>=22.1.0; extra == "full"
Requires-Dist: fastapi>=0.75.0; extra == "full"
Requires-Dist: flake8>=4.0.0; extra == "full"
Requires-Dist: gruut>=2.0.0; platform_system != "Windows" and extra == "full"
Requires-Dist: inflect>=5.3.0; extra == "full"
Requires-Dist: isort>=5.10.0; extra == "full"
Requires-Dist: langchain>=0.0.139; extra == "full"
Requires-Dist: librosa==0.8.0; python_version < "3.10" and extra == "full"
Requires-Dist: mypy>=0.931; extra == "full"
Requires-Dist: numpy==1.19.3; python_version < "3.10" and extra == "full"
Requires-Dist: openai-whisper>=20230314; extra == "full"
Requires-Dist: phonemizer>=3.0.0; extra == "full"
Requires-Dist: praat-parselmouth>=0.4.0; extra == "full"
Requires-Dist: pvporcupine>=2.1.0; extra == "full"
Requires-Dist: pyctcdecode>=0.3.0; extra == "full"
Requires-Dist: pytest-cov>=3.0.0; extra == "full"
Requires-Dist: pytest>=7.0.0; extra == "full"
Requires-Dist: python-multipart>=0.0.5; extra == "full"
Requires-Dist: resemblyzer>=0.1.0; extra == "full"
Requires-Dist: rich>=12.0.0; extra == "full"
Requires-Dist: sphinx-rtd-theme>=1.0.0; extra == "full"
Requires-Dist: sphinx>=4.4.0; extra == "full"
Requires-Dist: tensorflow==1.15.0; python_version < "3.10" and extra == "full"
Requires-Dist: torch>=1.10.0; extra == "full"
Requires-Dist: torchaudio>=0.10.0; extra == "full"
Requires-Dist: transformers>=4.18.0; extra == "full"
Requires-Dist: typer>=0.4.0; extra == "full"
Requires-Dist: unidecode>=1.3.0; extra == "full"
Requires-Dist: uvicorn>=0.17.0; extra == "full"
Requires-Dist: webrtcvad==2.0.10; extra == "full"
Requires-Dist: webrtcvad>=2.0.10; extra == "full"
Dynamic: author
Dynamic: author-email
Dynamic: classifier
Dynamic: description
Dynamic: description-content-type
Dynamic: home-page
Dynamic: license-file
Dynamic: project-url
Dynamic: provides-extra
Dynamic: requires-dist
Dynamic: requires-python
Dynamic: summary
